rasal/__init__.py
rasal/_lens.py
rasal/_resolution.py
rasal/_sensor.py
rasal/_version.py
rasal/units.py
rasal-0.1.0.dist-info/AUTHORS.rst
rasal-0.1.0.dist-info/LICENSE
rasal-0.1.0.dist-info/METADATA
rasal-0.1.0.dist-info/WHEEL
rasal-0.1.0.dist-info/top_level.txt
rasal-0.1.0.dist-info/RECORD
